brugernavn/__init__.py
brugernavn/__main__.py
brugernavn/brugernavn.py
brugernavn/ressources/data.json
brugernavn/ressources/tests.json
brugernavn/test_brugernavn.py
brugernavn/test_typer.py
brugernavn-0.2.0.dist-info/LICENSE
brugernavn-0.2.0.dist-info/METADATA
brugernavn-0.2.0.dist-info/WHEEL
brugernavn-0.2.0.dist-info/RECORD
