Metadata-Version: 2.1
Name: brugernavn
Version: 0.2.0
Summary: An OSINT tool to search for a username on many websites
Home-page: https://edugit.org/pinguin/brugernavn
License: MIT
Keywords: osint,osint tool,search,username
Author: Jonathan Krüger
Author-email: jonathan.krueger@teckids.org
Requires-Python: >=3.9,<4.0
Classifier: License :: OSI Approved :: MIT License
Classifier: Programming Language :: Python :: 3
Classifier: Programming Language :: Python :: 3.9
Classifier: Programming Language :: Python :: 3.10
Classifier: Programming Language :: Python :: 3.11
Classifier: Programming Language :: Python :: 3
Requires-Dist: requests (>=2.28.2,<3.0.0)
Requires-Dist: typer (>=0.7.0,<0.8.0)
Project-URL: Repository, https://edugit.org/pinguin/brugernavn
